neos/__init__.py
neos/_version.py
neos/losses.py
neos/py.typed
neos/top_level.py
neos-0.3.0.dist-info/LICENSE
neos-0.3.0.dist-info/METADATA
neos-0.3.0.dist-info/WHEEL
neos-0.3.0.dist-info/top_level.txt
neos-0.3.0.dist-info/RECORD
