Metadata-Version: 2.1
Name: neos
Version: 0.3.0
Summary: UpUpstream optimization of a neural net summary statistic with respect to downstream inference goals.
Home-page: https://github.com/gradhep/neos
Author: Nathan Simpson
Author-email: n.s@cern.ch
Maintainer: Nathan Simpson
Maintainer-email: n.s@cern.ch
License: BSD-3-Clause
Project-URL: Documentation, https://neos.readthedocs.io/
Project-URL: Bug Tracker, https://github.com/gradhep/neos/issues
Project-URL: Discussions, https://github.com/gradhep/neos/discussions
Project-URL: Changelog, https://github.com/gradhep/neos/releases
Platform: Any
Classifier: Development Status :: 1 - Planning
Classifier: Intended Audience :: Developers
Classifier: Intended Audience :: Science/Research
Classifier: License :: OSI Approved :: BSD License
Classifier: Operating System :: OS Independent
Classifier: Programming Language :: Python
Classifier: Programming Language :: Python :: 3
Classifier: Programming Language :: Python :: 3 :: Only
Classifier: Programming Language :: Python :: 3.6
Classifier: Programming Language :: Python :: 3.7
Classifier: Programming Language :: Python :: 3.8
Classifier: Programming Language :: Python :: 3.9
Classifier: Programming Language :: Python :: 3.10
Classifier: Topic :: Scientific/Engineering
Requires-Python: >=3.6
License-File: LICENSE
Requires-Dist: celluloid
Requires-Dist: matplotlib
Requires-Dist: relaxed (>=0.2.0)
Requires-Dist: sklearn
Requires-Dist: typing-extensions (>=3.7) ; python_version < "3.8"
Provides-Extra: dev
Requires-Dist: pytest (>=6) ; extra == 'dev'
Provides-Extra: docs
Requires-Dist: Sphinx (~=3.0) ; extra == 'docs'
Requires-Dist: myst-parser (>=0.13) ; extra == 'docs'
Requires-Dist: sphinx-book-theme (>=0.1.0) ; extra == 'docs'
Requires-Dist: sphinx-copybutton ; extra == 'docs'
Provides-Extra: test
Requires-Dist: pytest (>=6) ; extra == 'test'
